brandtemplate/__init__.py
brandtemplate/great_tables/gt_theme.py
brandtemplate/plotnine/plotnine_extra.py
brandtemplate/plotnine/plotnine_theme.py
brandtemplate/qmd_template/cli_import_template.py
brandtemplate/qmd_template/import_template.py
brandtemplate/template_files/_extension.yml
brandtemplate/template_files/background.css
brandtemplate/template_files/background.svg
brandtemplate/template_files/font/Inter-Bold.ttf
brandtemplate/template_files/font/Inter-BoldItalic.ttf
brandtemplate/template_files/font/Inter-Italic.ttf
brandtemplate/template_files/font/Inter-Regular.ttf
brandtemplate/template_files/font/LICENSE.txt
brandtemplate/template_files/fonts.css
brandtemplate/template_files/logo.svg
brandtemplate/template_files/section-background.svg
brandtemplate/template_files/template.qmd
brandtemplate/template_files/thank-you-background.svg
brandtemplate/template_files/theme.scss
brandtemplate/template_files/title-background.svg
brandtemplate-0.1.4.dist-info/METADATA
brandtemplate-0.1.4.dist-info/WHEEL
brandtemplate-0.1.4.dist-info/entry_points.txt
brandtemplate-0.1.4.dist-info/RECORD
