Metadata-Version: 2.1
Name: brandtemplate
Version: 0.1.4
Summary: Template for qmd presenations
Author: aplunket
Author-email: applunket@gmail.com
Requires-Python: >=3.9,<4.0
Classifier: Programming Language :: Python :: 3
Classifier: Programming Language :: Python :: 3.9
Classifier: Programming Language :: Python :: 3.10
Classifier: Programming Language :: Python :: 3.11
Classifier: Programming Language :: Python :: 3.12
Requires-Dist: great-tables (>=0.9.0,<0.10.0)
Requires-Dist: numpy (>=1.4,<2.0)
Requires-Dist: plotnine (>=0.13.6,<0.14.0)
Requires-Dist: presoutput (>=0.1.4,<0.2.0)
